qorus_remote/__init__.py
qorus_remote/tools/__init__.py
qorus_remote/tools/make_release.py
qorus_remote/tools/qorus_remote_commands.py
qorus_remote/tools/templates/install.sh
qorus_remote-1.0.5.dist-info/entry_points.txt
qorus_remote-1.0.5.dist-info/LICENSE
qorus_remote-1.0.5.dist-info/WHEEL
qorus_remote-1.0.5.dist-info/METADATA
qorus_remote-1.0.5.dist-info/RECORD
