Metadata-Version: 2.1
Name: qorus-remote
Version: 1.0.5
Summary: A package with scripts for use with remote Qorus instances
Home-page: https://qoretechnologies.com/
License: MIT
Keywords: qorus
Author: Qore Technologies, s.r.o.
Author-email: info@qoretechnologies.com
Requires-Python: >=3.8,<4.0
Classifier: Environment :: Console
Classifier: Environment :: Web Environment
Classifier: Intended Audience :: Developers
Classifier: Intended Audience :: Information Technology
Classifier: Intended Audience :: System Administrators
Classifier: License :: OSI Approved :: MIT License
Classifier: Operating System :: MacOS :: MacOS X
Classifier: Operating System :: Microsoft :: Windows
Classifier: Operating System :: POSIX
Classifier: Programming Language :: Python :: 3
Classifier: Programming Language :: Python :: 3.8
Classifier: Programming Language :: Python :: 3.9
Classifier: Programming Language :: Python :: 3.10
Classifier: Programming Language :: Python :: 3.11
Classifier: Topic :: Software Development
Classifier: Topic :: System :: Systems Administration
Classifier: Topic :: Utilities
Requires-Dist: pyaml
Requires-Dist: requests
Requires-Dist: urllib3
Requires-Dist: websocket-client
Project-URL: Bug Tracker, https://github.com/qoretechnologies/qorus-remote/issues
Project-URL: Repository, https://github.com/qoretechnologies/qorus-remote
